simple_salesforce/__init__.py
simple_salesforce/__version__.py
simple_salesforce/api.py
simple_salesforce/bulk.py
simple_salesforce/bulk2.py
simple_salesforce/exceptions.py
simple_salesforce/format.py
simple_salesforce/login.py
simple_salesforce/messages.py
simple_salesforce/metadata.py
simple_salesforce/metadata.wsdl
simple_salesforce/py.typed
simple_salesforce/util.py
simple_salesforce-1.12.8.dist-info/licenses/LICENSE.txt
simple_salesforce-1.12.8.dist-info/METADATA
simple_salesforce-1.12.8.dist-info/WHEEL
simple_salesforce-1.12.8.dist-info/top_level.txt
simple_salesforce-1.12.8.dist-info/RECORD
