Metadata-Version: 2.4
Name: simple-salesforce
Version: 1.12.8
Summary: A basic Salesforce.com REST API client.
Author-email: Nick Catalano <nickcatal@gmail.com>
Maintainer-email: Jonathan Wobken <jonathanwobken@gmail.com>
License-Expression: Apache-2.0
Project-URL: Homepage, https://github.com/simple-salesforce/simple-salesforce
Project-URL: Documentation, https://simple-salesforce.readthedocs.io/
Project-URL: Repository, https://github.com/simple-salesforce/simple-salesforce.git
Project-URL: Bug Tracker, https://github.com/simple-salesforce/simple-salesforce/issues
Project-URL: Changelog, https://github.com/simple-salesforce/simple-salesforce/blob/master/CHANGES
Keywords: python,salesforce,salesforce.com,CRM,API,REST
Classifier: Development Status :: 5 - Production/Stable
Classifier: Intended Audience :: Developers
Classifier: Intended Audience :: System Administrators
Classifier: Operating System :: OS Independent
Classifier: Topic :: Internet :: WWW/HTTP
Classifier: Programming Language :: Python :: 3.9
Classifier: Programming Language :: Python :: 3.10
Classifier: Programming Language :: Python :: 3.11
Classifier: Programming Language :: Python :: 3.12
Classifier: Programming Language :: Python :: 3.13
Classifier: Programming Language :: Python :: Implementation :: PyPy
Requires-Python: >=3.9
License-File: LICENSE.txt
Requires-Dist: requests>=2.22.0
Requires-Dist: typing-extensions
Requires-Dist: zeep
Requires-Dist: pyjwt[crypto]
Requires-Dist: more-itertools
Provides-Extra: test
Requires-Dist: pytest; extra == "test"
Requires-Dist: pytest-cov; extra == "test"
Requires-Dist: coverage; extra == "test"
Requires-Dist: pytz>=2014.1.1; extra == "test"
Requires-Dist: responses>=0.5.1; extra == "test"
Requires-Dist: cryptography>4.0.0; extra == "test"
Provides-Extra: lint
Requires-Dist: pylint; extra == "lint"
Requires-Dist: mypy; extra == "lint"
Requires-Dist: types-requests; extra == "lint"
Requires-Dist: types-pytz; extra == "lint"
Provides-Extra: format
Requires-Dist: black; extra == "format"
Requires-Dist: isort; extra == "format"
Requires-Dist: flake8; extra == "format"
Requires-Dist: flake8-docstrings; extra == "format"
Provides-Extra: dev
Requires-Dist: simple-salesforce[format,lint,test]; extra == "dev"
Requires-Dist: tox; extra == "dev"
Requires-Dist: pre-commit; extra == "dev"
Dynamic: license-file
Dynamic: requires-python
